novainstrumentation/ARparameters.py
novainstrumentation/__init__.py
novainstrumentation/figtools.py
novainstrumentation/filter.py
novainstrumentation/freq_analysis.py
novainstrumentation/niplot.py
novainstrumentation/peakdelta.py
novainstrumentation/peaks.py
novainstrumentation/smooth.py
novainstrumentation/stat_analysis.py
novainstrumentation/tictac.py
novainstrumentation/tools.py
novainstrumentation/data/bvp.txt
novainstrumentation/data/cleanecg.txt
novainstrumentation/data/eda.txt
novainstrumentation/data/emg.txt
novainstrumentation/data/force.txt
novainstrumentation/data/noisyecg.txt
novainstrumentation/data/resp.txt
novainstrumentation/data/switch.txt
novainstrumentation/data/xyz.txt
novainstrumentation/data/xyzcal.txt
novainstrumentation/data/xyzcal_std_values.txt
novainstrumentation/panthomkins/__init__.py
novainstrumentation/panthomkins/butterworth_filters.py
novainstrumentation/panthomkins/detect_panthomkins_peaks.py
novainstrumentation/panthomkins/panthomkins.py
novainstrumentation/panthomkins/rr_update.py
novainstrumentation/tests/__init__.py
novainstrumentation/tests/test_filter.py
novainstrumentation/tests/test_peaks.py
novainstrumentation/tests/test_smooth.py
novainstrumentation/tests/test_tools.py
novainstrumentation/tests/test_waves.py
novainstrumentation/waves/__init__.py
novainstrumentation/waves/alignWaves.py
novainstrumentation/waves/computemeanwave.py
novainstrumentation/waves/frequencyAlignDistance.py
novainstrumentation/waves/getarray.py
novainstrumentation/waves/meanwave.py
novainstrumentation/waves/plotheatmap.py
novainstrumentation/waves/plotheatmap2.py
novainstrumentation/waves/stdwave.py
novainstrumentation/waves/sumvolve.py
novainstrumentation/waves/wavedistance.py
novainstrumentation/waves/waves.py
novainstrumentation-0.2.dist-info/DESCRIPTION.rst
novainstrumentation-0.2.dist-info/METADATA
novainstrumentation-0.2.dist-info/RECORD
novainstrumentation-0.2.dist-info/WHEEL
novainstrumentation-0.2.dist-info/metadata.json
novainstrumentation-0.2.dist-info/top_level.txt
